break_out_nested/LICENSE
break_out_nested/README.MD
break_out_nested/__init__.py
break_out_nested/requirements.txt
break_out_nested/thirdparty.json
break_out_nested-0.10.dist-info/LICENSE.rst
break_out_nested-0.10.dist-info/METADATA
break_out_nested-0.10.dist-info/WHEEL
break_out_nested-0.10.dist-info/top_level.txt
break_out_nested-0.10.dist-info/RECORD
